{"file":"shangcheng.png","frames":{
"tablebk":{"x":1551,"y":1203,"w":99,"h":85,"offX":0,"offY":0,"sourceW":99,"sourceH":85},
"buy0":{"x":1283,"y":364,"w":552,"h":361,"offX":0,"offY":1,"sourceW":552,"sourceH":362},
"buy1":{"x":1332,"y":1309,"w":163,"h":66,"offX":1,"offY":0,"sourceW":165,"sourceH":67},
"buy2":{"x":1167,"y":1309,"w":163,"h":66,"offX":1,"offY":0,"sourceW":165,"sourceH":67},
"coinBtn_select":{"x":1280,"y":727,"w":81,"h":42,"offX":65,"offY":32,"sourceW":213,"sourceH":128},
"daojuBtn_select":{"x":1195,"y":723,"w":83,"h":42,"offX":65,"offY":32,"sourceW":213,"sourceH":128},
"gift1":{"x":1377,"y":1377,"w":104,"h":67,"offX":22,"offY":37,"sourceW":154,"sourceH":104},
"gift2":{"x":1337,"y":1203,"w":112,"h":93,"offX":14,"offY":11,"sourceW":154,"sourceH":104},
"gift3":{"x":1497,"y":1309,"w":117,"h":92,"offX":12,"offY":0,"sourceW":154,"sourceH":104},
"gift4":{"x":1451,"y":1203,"w":98,"h":96,"offX":12,"offY":0,"sourceW":154,"sourceH":104},
"gift5":{"x":1195,"y":1203,"w":140,"h":104,"offX":3,"offY":0,"sourceW":154,"sourceH":104},
"gold":{"x":1162,"y":1403,"w":213,"h":128,"offX":0,"offY":0,"sourceW":213,"sourceH":128},
"line":{"x":1162,"y":1533,"w":683,"h":2,"offX":0,"offY":0,"sourceW":683,"sourceH":2},
"list_bg_g0":{"x":1,"y":1539,"w":1149,"h":134,"offX":32,"offY":0,"sourceW":1192,"sourceH":134},
"list_bg_g1":{"x":1,"y":1267,"w":1164,"h":134,"offX":28,"offY":0,"sourceW":1192,"sourceH":134},
"list_bg_g2":{"x":1,"y":995,"w":1192,"h":134,"offX":0,"offY":0,"sourceW":1192,"sourceH":134},
"list_bg0":{"x":1,"y":723,"w":1192,"h":134,"offX":0,"offY":0,"sourceW":1192,"sourceH":134},
"list_bg1":{"x":1,"y":859,"w":1192,"h":134,"offX":0,"offY":0,"sourceW":1192,"sourceH":134},
"list_bg2":{"x":1,"y":1403,"w":1159,"h":134,"offX":33,"offY":0,"sourceW":1192,"sourceH":134},
"list_bg3":{"x":1,"y":1131,"w":1164,"h":134,"offX":28,"offY":0,"sourceW":1192,"sourceH":134},
"mall_bg":{"x":1,"y":1,"w":1280,"h":720,"offX":0,"offY":0,"sourceW":1280,"sourceH":720},
"ower":{"x":1167,"y":1131,"w":213,"h":70,"offX":3,"offY":0,"sourceW":216,"sourceH":70},
"pay0":{"x":1283,"y":1,"w":552,"h":361,"offX":0,"offY":1,"sourceW":552,"sourceH":362},
"PropBtn1":{"x":1152,"y":1539,"w":213,"h":128,"offX":0,"offY":0,"sourceW":213,"sourceH":128},
"renmingbi (2)":{"x":1195,"y":767,"w":40,"h":40,"offX":0,"offY":0,"sourceW":40,"sourceH":40},
"renmingbi":{"x":1195,"y":767,"w":40,"h":40,"offX":0,"offY":0,"sourceW":40,"sourceH":40}}}